gocept/pagelet/README.rst
gocept/pagelet/__init__.py
gocept/pagelet/meta.zcml
gocept/pagelet/test-template.pt
gocept/pagelet/viewletpage.py
gocept/pagelet/zcml.py
gocept_pagelet-2.1.dist-info/licenses/LICENSE.txt
gocept_pagelet-2.1.dist-info/METADATA
gocept_pagelet-2.1.dist-info/WHEEL
gocept_pagelet-2.1.dist-info/top_level.txt
gocept_pagelet-2.1.dist-info/RECORD
