Metadata-Version: 2.4
Name: gocept.pagelet
Version: 2.1
Summary: Easier z3c.pagelet handling
Home-page: https://github.com/gocept/gocept.pagelet
Author: Christian Zagrodnick
Author-email: mail@gocept.com
License: ZPL 2.1
Keywords: easy z3c.pagelet zope3 pagelet zope
Classifier: Development Status :: 5 - Production/Stable
Classifier: Framework :: Zope3
Classifier: Intended Audience :: Developers
Classifier: License :: OSI Approved
Classifier: License :: OSI Approved :: Zope Public License
Classifier: Natural Language :: English
Classifier: Operating System :: OS Independent
Classifier: Programming Language :: Python
Classifier: Programming Language :: Python :: 3
Classifier: Programming Language :: Python :: 3.7
Classifier: Programming Language :: Python :: 3.8
Classifier: Programming Language :: Python :: 3.9
Classifier: Programming Language :: Python :: 3.10
Classifier: Programming Language :: Python :: 3.11
Classifier: Programming Language :: Python :: Implementation :: CPython
Classifier: Programming Language :: Python :: Implementation :: PyPy
Classifier: Topic :: Software Development :: Libraries
Classifier: Topic :: Software Development :: Libraries :: Python Modules
Requires-Python: >=3.7
License-File: LICENSE.txt
Requires-Dist: zope.interface
Requires-Dist: zope.component
Requires-Dist: zope.publisher
Requires-Dist: zope.viewlet
Requires-Dist: z3c.template
Requires-Dist: z3c.pagelet
Requires-Dist: zope.browsermenu
Requires-Dist: zope.browserpage
Provides-Extra: test
Requires-Dist: zope.testing; extra == "test"
Dynamic: author
Dynamic: author-email
Dynamic: classifier
Dynamic: description
Dynamic: home-page
Dynamic: keywords
Dynamic: license
Dynamic: license-file
Dynamic: provides-extra
Dynamic: requires-dist
Dynamic: requires-python
Dynamic: summary
